{
	"head": {
		"vars": [ "s", "p", "o" ]
	}, 
	"results": {
		"bindings": [
			{
				"s": { "type": "uri", "value": "http:\/\/collection.britishmuseum.org\/id\/thesauri\/dimension\/height" }, 
				"o": { "type": "literal", "value": "Height" }, 
				"p": { "type": "uri", "value": "http:\/\/www.w3.org\/2004\/02\/skos\/core#prefLabel" }
			}, 
			{
				"s": { "type": "uri", "value": "http:\/\/collection.britishmuseum.org\/id\/thesauri\/dimension\/thickness" }, 
				"o": { "type": "literal", "value": "Thickness" }, 
				"p": { "type": "uri", "value": "http:\/\/www.w3.org\/2004\/02\/skos\/core#prefLabel" }
			}, 
			{
				"s": { "type": "uri", "value": "http:\/\/collection.britishmuseum.org\/id\/thesauri\/dimension\/width" }, 
				"o": { "type": "literal", "value": "Width" }, 
				"p": { "type": "uri", "value": "http:\/\/www.w3.org\/2004\/02\/skos\/core#prefLabel" }
			}, 
			{
				"s": { "type": "uri", "value": "http:\/\/collection.britishmuseum.org\/id\/thesauri\/dimension\/diameter" }, 
				"o": { "type": "literal", "value": "Diameter" }, 
				"p": { "type": "uri", "value": "http:\/\/www.w3.org\/2004\/02\/skos\/core#prefLabel" }
			}, 
			{
				"s": { "type": "uri", "value": "http:\/\/collection.britishmuseum.org\/id\/thesauri\/dimension\/length" }, 
				"o": { "type": "literal", "value": "Length" }, 
				"p": { "type": "uri", "value": "http:\/\/www.w3.org\/2004\/02\/skos\/core#prefLabel" }
			}, 
			{
				"s": { "type": "uri", "value": "http:\/\/collection.britishmuseum.org\/id\/thesauri\/dimension\/depth" }, 
				"o": { "type": "literal", "value": "Depth" }, 
				"p": { "type": "uri", "value": "http:\/\/www.w3.org\/2004\/02\/skos\/core#prefLabel" }
			}, 
			{
				"s": { "type": "uri", "value": "http:\/\/collection.britishmuseum.org\/id\/thesauri\/dimension\/weight" }, 
				"o": { "type": "literal", "value": "Weight" }, 
				"p": { "type": "uri", "value": "http:\/\/www.w3.org\/2004\/02\/skos\/core#prefLabel" }
			}, 
			{
				"s": { "type": "uri", "value": "http:\/\/collection.britishmuseum.org\/id\/thesauri\/dimension\/circumference" }, 
				"o": { "type": "literal", "value": "Circumference" }, 
				"p": { "type": "uri", "value": "http:\/\/www.w3.org\/2004\/02\/skos\/core#prefLabel" }
			}, 
			{
				"s": { "type": "uri", "value": "http:\/\/collection.britishmuseum.org\/id\/thesauri\/dimension\/volume" }, 
				"o": { "type": "literal", "value": "Volume" }, 
				"p": { "type": "uri", "value": "http:\/\/www.w3.org\/2004\/02\/skos\/core#prefLabel" }
			}, 
			{
				"s": { "type": "uri", "value": "http:\/\/collection.britishmuseum.org\/id\/thesauri\/dimension\/curvature" }, 
				"o": { "type": "literal", "value": "Curvature" }, 
				"p": { "type": "uri", "value": "http:\/\/www.w3.org\/2004\/02\/skos\/core#prefLabel" }
			}, 
			{
				"s": { "type": "uri", "value": "http:\/\/collection.britishmuseum.org\/id\/thesauri\/dimension\/percentage" }, 
				"o": { "type": "literal", "value": "Percentage" }, 
				"p": { "type": "uri", "value": "http:\/\/www.w3.org\/2004\/02\/skos\/core#prefLabel" }
			}, 
			{
				"s": { "type": "uri", "value": "http:\/\/collection.britishmuseum.org\/id\/thesauri\/dimension\/currency" }, 
				"o": { "type": "literal", "value": "Currency" }, 
				"p": { "type": "uri", "value": "http:\/\/www.w3.org\/2004\/02\/skos\/core#prefLabel" }
			}, 
			{
				"s": { "type": "uri", "value": "http:\/\/collection.britishmuseum.org\/id\/thesauri\/dimension\/die-axis" }, 
				"o": { "type": "literal", "value": "Die-axis" }, 
				"p": { "type": "uri", "value": "http:\/\/www.w3.org\/2004\/02\/skos\/core#prefLabel" }
			}
		]
	}
}